<?xml version="1.0" encoding="utf-8" ?>
<dwsync>
<file name="3255.png" server="ftp.dylanhalpern.com" local="131882638479337120" remote="131882818800000000" Dst="1" />
<file name="3256.png" server="ftp.dylanhalpern.com" local="131882638979265843" remote="131882818800000000" Dst="1" />
<file name="3258.png" server="ftp.dylanhalpern.com" local="131882639160485038" remote="131882818800000000" Dst="1" />
<file name="3257.png" server="ftp.dylanhalpern.com" local="131882639022040089" remote="131882818800000000" Dst="1" />
<file name="3259.png" server="ftp.dylanhalpern.com" local="131882639239268631" remote="131882818800000000" Dst="1" />
<file name="3260.png" server="ftp.dylanhalpern.com" local="131882639740643178" remote="131882818800000000" Dst="1" />
<file name="3261.png" server="ftp.dylanhalpern.com" local="131882639760169713" remote="131882818800000000" Dst="1" />
<file name="3262.png" server="ftp.dylanhalpern.com" local="131882639816644400" remote="131882818800000000" Dst="1" />
<file name="3263.png" server="ftp.dylanhalpern.com" local="131882639830672623" remote="131882818800000000" Dst="1" />
<file name="3264.png" server="ftp.dylanhalpern.com" local="131882657063498064" remote="131882818800000000" Dst="1" />
<file name="3266.png" server="ftp.dylanhalpern.com" local="131882657135490698" remote="131882818800000000" Dst="1" />
<file name="3265.png" server="ftp.dylanhalpern.com" local="131882657081196950" remote="131882818800000000" Dst="1" />
<file name="3267.png" server="ftp.dylanhalpern.com" local="131882657152687351" remote="131882818800000000" Dst="1" />
<file name="3269.png" server="ftp.dylanhalpern.com" local="131882657369298548" remote="131882818800000000" Dst="1" />
<file name="3268.png" server="ftp.dylanhalpern.com" local="131882657351785851" remote="131882818800000000" Dst="1" />
<file name="3270.png" server="ftp.dylanhalpern.com" local="131882657425596164" remote="131882818800000000" Dst="1" />
<file name="3272.png" server="ftp.dylanhalpern.com" local="131882657646304291" remote="131882818800000000" Dst="1" />
<file name="3271.png" server="ftp.dylanhalpern.com" local="131882657441883535" remote="131882818800000000" Dst="1" />
<file name="3273.png" server="ftp.dylanhalpern.com" local="131882657663154885" remote="131882818800000000" Dst="1" />
<file name="3274.png" server="ftp.dylanhalpern.com" local="131882657714781713" remote="131882818800000000" Dst="1" />
<file name="3275.png" server="ftp.dylanhalpern.com" local="131882657729902740" remote="131882818800000000" Dst="1" />
<file name="3276.png" server="ftp.dylanhalpern.com" local="131882657926413712" remote="131882818800000000" Dst="1" />
<file name="3277.png" server="ftp.dylanhalpern.com" local="131882657941427623" remote="131882818800000000" Dst="1" />
<file name="3278.png" server="ftp.dylanhalpern.com" local="131882657991336228" remote="131882818800000000" Dst="1" />
<file name="3279.png" server="ftp.dylanhalpern.com" local="131882658008172422" remote="131882818800000000" Dst="1" />
<file name="3280.png" server="ftp.dylanhalpern.com" local="131882658202209874" remote="131882818800000000" Dst="1" />
<file name="3282.png" server="ftp.dylanhalpern.com" local="131882658270282242" remote="131882818800000000" Dst="1" />
<file name="3281.png" server="ftp.dylanhalpern.com" local="131882658218892167" remote="131882818800000000" Dst="1" />
<file name="3283.png" server="ftp.dylanhalpern.com" local="131882658285647146" remote="131882818800000000" Dst="1" />
<file name="3284.png" server="ftp.dylanhalpern.com" local="131882658480146251" remote="131882818800000000" Dst="1" />
<file name="3285.png" server="ftp.dylanhalpern.com" local="131882658495946457" remote="131882818800000000" Dst="1" />
<file name="3286.png" server="ftp.dylanhalpern.com" local="131882658548547379" remote="131882818800000000" Dst="1" />
<file name="3288.png" server="ftp.dylanhalpern.com" local="131882658757745524" remote="131882818800000000" Dst="1" />
<file name="3287.png" server="ftp.dylanhalpern.com" local="131882658564065401" remote="131882818800000000" Dst="1" />
<file name="3290.png" server="ftp.dylanhalpern.com" local="131882658827234164" remote="131882818800000000" Dst="1" />
<file name="3289.png" server="ftp.dylanhalpern.com" local="131882658773423671" remote="131882818800000000" Dst="1" />
<file name="3291.png" server="ftp.dylanhalpern.com" local="131882658843078655" remote="131882818800000000" Dst="1" />
<file name="3293.png" server="ftp.dylanhalpern.com" local="131882659055822714" remote="131882818800000000" Dst="1" />
<file name="3294.png" server="ftp.dylanhalpern.com" local="131882659105224203" remote="131882818800000000" Dst="1" />
<file name="3292.png" server="ftp.dylanhalpern.com" local="131882659040470875" remote="131882818800000000" Dst="1" />
<file name="3295.png" server="ftp.dylanhalpern.com" local="131882659121900815" remote="131882818800000000" Dst="1" />
<file name="3296.png" server="ftp.dylanhalpern.com" local="131882663511981399" remote="131882818800000000" Dst="1" />
<file name="3297.png" server="ftp.dylanhalpern.com" local="131882663535835394" remote="131882818800000000" Dst="1" />
<file name="3298.png" server="ftp.dylanhalpern.com" local="131882663606594364" remote="131882818800000000" Dst="1" />
<file name="3299.png" server="ftp.dylanhalpern.com" local="131882663628139894" remote="131882818800000000" Dst="1" />
<file name="3300.png" server="ftp.dylanhalpern.com" local="131882663882741454" remote="131882818800000000" Dst="1" />
<file name="3301.png" server="ftp.dylanhalpern.com" local="131882663906967349" remote="131882818800000000" Dst="1" />
<file name="3302.png" server="ftp.dylanhalpern.com" local="131882663961773603" remote="131882818800000000" Dst="1" />
<file name="3303.png" server="ftp.dylanhalpern.com" local="131882663977826813" remote="131882818800000000" Dst="1" />
</dwsync>